README.md
setup.cfg
setup.py
pycrybittrex/__init__.py
pycrybittrex/bittrex.py
pycrybittrex/definitions.py
pycrybittrex.egg-info/PKG-INFO
pycrybittrex.egg-info/SOURCES.txt
pycrybittrex.egg-info/dependency_links.txt
pycrybittrex.egg-info/requires.txt
pycrybittrex.egg-info/top_level.txt
pycrybittrex/core/__init__.py
pycrybittrex/core/bittrex11.py
pycrybittrex/core/bittrex20.py
pycrybittrex/core/bittrexbase.py
pycrybittrex/core/urlutils.py