Metadata-Version: 1.1
Name: pycrybittrex
Version: 0.4.0
Summary: bittrex python client
Home-page: https://github.com/namiazad/pycrybittrex
Author: namiazad
Author-email: nami.nasserazad@gmail.com
License: UNKNOWN
Download-URL: https://github.com/namiazad/pycrybittrex/archive/0.4.0.tar.gz
Keywords: python,bittrex
Platform: UNKNOWN
